[
    {
        "id": 1,
        "label": "Le côté lumineux",
        "href": "lumineux"
    },
    {
        "id": 2,
        "label": "Le côté obscure",
        "href": "obscure"
    },
    {
        "id": 3,
        "label": "L'empire",
        "href": "empire"
    },
    {
        "id": 4,
        "label": "Les droïdes",
        "href": "droides"
    },
    {
        "id": 5,
        "label": "Les ewoks",
        "href": "ewoks"
    },
    {
        "id": 6,
        "label": "Jabba le Hutt",
        "href": "jabba"
    }
]
